CHANGELOG.txt
LICENSE.txt
MANIFEST.in
README.txt
aladelca_gre.py
setup.py
gre_aladelca.egg-info/PKG-INFO
gre_aladelca.egg-info/SOURCES.txt
gre_aladelca.egg-info/dependency_links.txt
gre_aladelca.egg-info/top_level.txt