Metadata-Version: 2.1
Name: gre-aladelca
Version: 0.0.1
Summary: ES: Principales cálculos para GRE, EN: Main calculations for GRE Exam
Home-page: https://linktr.ee/aladelca
Author: Carlos Adrian Alarcon
Author-email: alarcon.adrianc@gmail.com
License: MIT
Keywords: gre,calculations
Platform: UNKNOWN
Classifier: Development Status :: 5 - Production/Stable
Classifier: Intended Audience :: Education
Classifier: Operating System :: MacOS :: MacOS X
Classifier: Operating System :: Microsoft :: Windows
Classifier: Operating System :: POSIX
Classifier: License :: OSI Approved :: MIT License
Classifier: Programming Language :: Python :: 3
License-File: LICENSE.txt
